AUTHORS.rst
HISTORY.rst
LICENSE
MANIFEST.in
Makefile
README.rst
setup.py
Tests/.gitignore
Tests/__init__.py
Tests/__init__.pyc
Tests/test_ChainContext.py
Tests/test_CosmoHammerSampler.py
Tests/test_InMemoryStorageUtil.py
Tests/test_LikelihoodComputationChain.py
Tests/test_MpiUtil.py
Tests/test_Params.py
Tests/test_ParticleSwarmOptimizer.py
Tests/test_PositionGenerators.py
Tests/test_SampleFileUtil.py
cosmoHammer/ChainContext.py
cosmoHammer/ConcurrentMpiCosmoHammerSampler.py
cosmoHammer/Constants.py
cosmoHammer/CosmoHammerSampler.py
cosmoHammer/LikelihoodComputationChain.py
cosmoHammer/MpiCosmoHammerSampler.py
cosmoHammer/__init__.py
cosmoHammer/exceptions.py
cosmoHammer.egg-info/PKG-INFO
cosmoHammer.egg-info/SOURCES.txt
cosmoHammer.egg-info/dependency_links.txt
cosmoHammer.egg-info/requires.txt
cosmoHammer.egg-info/top_level.txt
cosmoHammer/modules/MultivarianteGaussianModule.py
cosmoHammer/modules/PseudoCmbModule.py
cosmoHammer/modules/RosenbrockModule.py
cosmoHammer/modules/__init__.py
cosmoHammer/pso/BestFitPositionGenerator.py
cosmoHammer/pso/CurvatureFitter.py
cosmoHammer/pso/MpiParticleSwarmOptimizer.py
cosmoHammer/pso/ParticleSwarmOptimizer.py
cosmoHammer/pso/__init__.py
cosmoHammer/util/FlatPositionGenerator.py
cosmoHammer/util/IPythonUtil.py
cosmoHammer/util/InMemoryStorageUtil.py
cosmoHammer/util/IterationStopCriteriaStrategy.py
cosmoHammer/util/MpiUtil.py
cosmoHammer/util/Params.py
cosmoHammer/util/SampleBallPositionGenerator.py
cosmoHammer/util/SampleFileUtil.py
cosmoHammer/util/__init__.py
examples/DerivedParamterFileUtil.py
examples/DummyCoreModule.py
examples/DummyLikelihoodModule.py
examples/__init__.py
examples/runCosmoHammer.py
examples/runCosmoHammerGaussian.py
examples/runCosmoHammerPseudoCmb.py
examples/runCosmoHammerRosenbrock.py
examples/wmap_tester.py
tests/__init__.py
tests/test_ChainContext.py
tests/test_CosmoHammerSampler.py
tests/test_InMemoryStorageUtil.py
tests/test_LikelihoodComputationChain.py
tests/test_MpiUtil.py
tests/test_Params.py
tests/test_ParticleSwarmOptimizer.py
tests/test_PositionGenerators.py
tests/test_SampleFileUtil.py