Metadata-Version: 1.1
Name: cosmoHammer
Version: 0.6.1
Summary: Cosmological parameter estimation with the MCMC Hammer
Home-page: http://www.cosmology.ethz.ch/research/software-lab/cosmohammer.html
Author: Joel Akeret
Author-email: jakeret@phys.ethz.ch
License: GPLv3
Keywords: CosmoHammer,parameter estimation,cosmology,MCMC
Platform: UNKNOWN
Classifier: Development Status :: 4 - Beta
Classifier: Intended Audience :: Science/Research
Classifier: Operating System :: OS Independent
Classifier: Programming Language :: Python
Classifier: Natural Language :: English
Classifier: Programming Language :: Python :: 2.7
Classifier: Programming Language :: Python :: 3.6
